{
  "gitSyncId": "699387b8cf3d5e4f99911848_5506f3ac-fa3d-4176-b9bb-66926a9e8bfb",
  "id": "Orders_deleteProductionRun",
  "pluginId": "postgres-plugin",
  "pluginType": "DB",
  "unpublishedAction": {
    "actionConfiguration": {
      "body": "DELETE FROM production_runs WHERE id = {{tblOrderRuns.triggeredRow.id}};",
      "encodeParamsToggle": true,
      "paginationType": "NONE",
      "pluginSpecifiedTemplates": [
        {
          "value": true
        }
      ],
      "timeoutInMillisecond": 10000
    },
    "confirmBeforeExecute": false,
    "datasource": {
      "id": "Access MRP",
      "isAutoGenerated": false,
      "name": "Access MRP",
      "pluginId": "postgres-plugin"
    },
    "dynamicBindingPathList": [
      {
        "key": "body"
      }
    ],
    "name": "deleteProductionRun",
    "pageId": "Orders",
    "runBehaviour": "MANUAL",
    "userSetOnLoad": false
  }
}